{"cfgData":{"code":"signMaterialsUpload","frames":[{"code":"T0008","name":"签约材料上传","orderBy":0,"sections":[{"code":"JKRCL","name":"借款人材料","orderBy":0,"segments":[{"code":"qyzp","empty":0,"fieldName":"qyzp","name":"签约照片","orderBy":0,"type":9},{"code":"qysp1","empty":0,"fieldName":"qysp1","name":"签约视频一","orderBy":0,"type":9},{"code":"qysp2","empty":0,"fieldName":"qysp2","name":"签约视频二","orderBy":0,"type":9},{"code":"qysp3","empty":0,"fieldName":"qysp3","name":"签约视频三","orderBy":0,"type":9},{"code":"\r\nqykbhtqzy","empty":0,"fieldName":"\r\nqykbhtqzy","name":"空白合同签字页","orderBy":0,"type":9},{"code":"qywzht1","empty":0,"fieldName":"qywzht1","name":"完整合同第一页","orderBy":0,"type":9},{"code":"qywzht2","empty":0,"fieldName":"qywzht2","name":"完整合同第二页","orderBy":0,"type":9},{"code":"qywzht3","empty":0,"fieldName":"qywzht3","name":"完整合同第三页","orderBy":0,"type":9},{"code":"jkhtsy","empty":0,"fieldName":"jkhtsy","name":"借款合同首页","orderBy":0,"type":9},{"code":"jkhtqzy","empty":0,"fieldName":"jkhtqzy","name":"借款合同签字页","orderBy":0,"type":9},{"code":"gcxy","empty":0,"fieldName":"gcxy","name":"购车协议","orderBy":0,"type":9},{"code":"dyhtsy","empty":0,"fieldName":"dyhtsy","name":"抵押合同首页","orderBy":0,"type":9},{"code":"dyhtqzy","empty":0,"fieldName":"dyhtqzy","name":"抵押合同签字页","orderBy":0,"type":9},{"code":"bzhtsy","empty":0,"fieldName":"bzhtsy","name":"保证合同首页","orderBy":0,"type":9},{"code":"bzhtqzy","empty":0,"fieldName":"bzhtqzy","name":"保证合同签字页","orderBy":0,"type":9},{"code":"gtyhcls","empty":0,"fieldName":"gtyhcls","name":"共同还款承诺书","orderBy":0,"type":9},{"code":"kfqywdlsy","empty":0,"fieldName":"kfqywdlsy","name":"卡分期业务代理协议","orderBy":0,"type":9},{"code":"gxht","empty":0,"fieldName":"gxht","name":"购销合同","orderBy":0,"type":9}]},{"code":"GTHKRCL","name":"共同还款人材料","orderBy":1,"segments":[{"code":"bzhtqzy","empty":0,"fieldName":"bzhtqzy","name":"保证合同签字页","orderBy":0,"type":9},{"code":"gtyhcls","empty":0,"fieldName":"gtyhcls","name":"共同还款承诺书","orderBy":0,"type":9},{"code":"kfqywdlsy","empty":0,"fieldName":"kfqywdlsy","name":"卡分期业务代理协议","orderBy":0,"type":9},{"code":"gxht","empty":0,"fieldName":"gxht","name":"购销合同","orderBy":0,"type":9},{"code":"qyzp","empty":0,"fieldName":"qyzp","name":"签约照片","orderBy":0,"type":9},{"code":"qysp1","empty":0,"fieldName":"qysp1","name":"签约视频一","orderBy":0,"type":9},{"code":"qysp2","empty":0,"fieldName":"qysp2","name":"签约视频二","orderBy":0,"type":9},{"code":"qysp3","empty":0,"fieldName":"qysp3","name":"签约视频三","orderBy":0,"type":9},{"code":"\r\nqykbhtqzy","empty":0,"fieldName":"\r\nqykbhtqzy","name":"空白合同签字页","orderBy":0,"type":9},{"code":"qywzht1","empty":0,"fieldName":"qywzht1","name":"完整合同第一页","orderBy":0,"type":9},{"code":"qywzht2","empty":0,"fieldName":"qywzht2","name":"完整合同第二页","orderBy":0,"type":9},{"code":"qywzht3","empty":0,"fieldName":"qywzht3","name":"完整合同第三页","orderBy":0,"type":9},{"code":"jkhtsy","empty":0,"fieldName":"jkhtsy","name":"借款合同首页","orderBy":0,"type":9},{"code":"jkhtqzy","empty":0,"fieldName":"jkhtqzy","name":"借款合同签字页","orderBy":0,"type":9},{"code":"gcxy","empty":0,"fieldName":"gcxy","name":"购车协议","orderBy":0,"type":9},{"code":"dyhtsy","empty":0,"fieldName":"dyhtsy","name":"抵押合同首页","orderBy":0,"type":9},{"code":"dyhtqzy","empty":0,"fieldName":"dyhtqzy","name":"抵押合同签字页","orderBy":0,"type":9},{"code":"bzhtsy","empty":0,"fieldName":"bzhtsy","name":"保证合同首页","orderBy":0,"type":9}]},{"code":"QTCL","name":"其他材料","orderBy":2,"segments":[]}]}],"name":"签约材料上传"},"code":0,"data":{"GTHKRCL":[{"accountLocation":"杭州上城","age":66,"averageDailyBalance":200.0000,"balance":5000.0000,"bankCard":"11112222333344466","company":"公司B22","companyAddress":"单位地址：BBB2","companyTel":"13334333307","companyZipcode":"310002","familyAddress":"家庭住址：BBB2223","familyTel":"0571-28881236","familyZipcode":"310003","houseStatus":1,"idCard":"330999939393939305","isDel":0,"isEnterprise":0,"isServe":0,"maritalStatus":0,"materials":[{"auditOpinion":"","auditResult":0,"id":10,"isDatamationBased":1,"isDel":0,"isNeedSensitive":1,"isSensitive":0,"materalsValidateResult":0,"materialsCode":"qz","materialsId":145,"materialsName":"A99 sign hetong","materialsPic":"http://hjhjkh.oss-cn-hangzhou.aliyuncs.com/carloan-test/IOS201702171047.jpg","materialsSourceResult":0,"materialsStatus":1,"materialsType":4,"orderNo":"nfdb2016102820480790","ownerCode":"GTHKRCL","sceneCode":"loanMaterialsUpload","thumbnailPic":"20161020/nfdb2016102000000355/tmbf_1476892815903-711490204.jpg","userId":100003,"userType":1}],"mobile":"13334333306","monthIncomeMoney":5000.000000,"orderNo":"nfdb2016102820480790","residentType":"603","sex":1,"userId":100003,"userName":"李四22","userRelationship":2,"userType":1,"userTypeCode":"GTHKRCL"},{"accountLocation":"杭州萧山","age":43,"averageDailyBalance":1111.0000,"balance":30000.0000,"bankCard":"11112222333344433","company":"公司B2","companyAddress":"单位地址：BBB","companyTel":"13334333305","companyZipcode":"310002","familyAddress":"家庭住址：BBB222","familyTel":"0571-28881234","familyZipcode":"310003","houseStatus":1,"idCard":"330999939393939303","isDel":0,"isEnterprise":0,"isServe":0,"maritalStatus":1,"materials":[{"auditOpinion":"","auditResult":0,"id":10312980,"isDatamationBased":1,"isDel":0,"isNeedSensitive":1,"isSensitive":0,"materalsValidateResult":0,"materialsCode":"hkbgry","materialsId":141,"materialsPic":"20161020/nfdb2016102000000355/1476892815903-711490204.jpg","materialsSourceResult":0,"materialsStatus":1,"orderNo":"nfdb2016102820480790","thumbnailPic":"20161020/nfdb2016102000000355/tmbf_1476892815903-711490204.jpg","userId":100001,"userType":1}],"mobile":"13334333309","monthIncomeMoney":5900.000000,"orderNo":"nfdb2016102820480790","residentType":"554,564,574","sex":0,"userId":100001,"userName":"李四","userRelationship":1,"userType":1,"userTypeCode":"GTHKRCL"}],"QTCL":[{"materials":[]}],"loanTask":{"approvalId":21,"assignee":1111,"category":"signMaterialsUpload","createDate":1484617804000,"createDateStr":"2017-01-17 09:50","id":4,"loanOrder":{"bankCode":"3221","busiAreaCode":2,"busiSourceId":1,"busiSourceTypeCode":"001","createDate":1481613850000,"createUser":14414,"demandBankId":82,"deptId":62,"id":100000,"idCard":"330621197410036801","isFirstLoaning":1,"isNeedVisit":1,"isSecond":1,"orderNo":"nfdb2016102820480790","orgId":62,"phone":"13399998889","processDefKey":"000000000000001","processInstId":"1243214215","realName":"张三2","remitAccountNumber":"1111111111111111111114","serviceTypeCode":"2","sourceOrderNo":"nfdb2016102820480799","status":0,"updateDate":1486958050000,"updateUser":1111},"orderNo":"nfdb2016102820480790","processTaskId":"234214213","sceneName":"签约材料上传","status":1},"JKRCL":[{"accountLocation":"杭州萧山","age":44,"averageDailyBalance":1222.0000,"balance":33333.0000,"bankCard":"11112222333344445","businessLicenseTime":1484496000000,"company":"公司A2","companyAddress":"单位地址：AAA","companyTel":"13388889999","companyZipcode":"310000","familyAddress":"家庭住址：BBB","familyTel":"0571-28881234","familyZipcode":"310001","houseStatus":1,"idCard":"330621197410036801","isDel":0,"isEnterprise":0,"isServe":0,"maritalStatus":1,"materials":[{"auditResult":0,"id":10875802,"isDel":0,"materialsCode":"asdadasd","materialsId":21211,"materialsPic":"http://hjhjkh.oss-cn-hangzhou.aliyuncs.com/carloan-test/10be68375edf151d976dc1b57ce9c30f.jpg","materialsType":0,"orderNo":"nfdb2016102820480790","sceneCode":"loanMaterialsUpload","userId":100000,"userType":0},{"auditResult":0,"id":10875804,"isDel":0,"materialsCode":"sbz","materialsId":212,"materialsPic":"http://hjhjkh.oss-cn-hangzhou.aliyuncs.com/carloan-test/74975199d51e3f5357f7ed3b3d099812.jpg","materialsType":0,"orderNo":"nfdb2016102820480790","sceneCode":"loanMaterialsUpload","userId":100000,"userType":0},{"auditResult":0,"id":10875805,"isDel":0,"materialsCode":"ccfgxy","materialsPic":"http://hjhjkh.oss-cn-hangzhou.aliyuncs.com/carloan-test/74975199d51e3f5357f7ed3b3d099812.jpg","materialsType":0,"orderNo":"nfdb2016102820480790","ownerCode":"0","sceneCode":"loanMaterialsUpload","userId":100000,"userType":0}],"mobile":"13399998889","monthIncomeMoney":7000.000000,"orderNo":"nfdb2016102820480790","residentType":"553,563,573","sex":1,"userId":100000,"userName":"张三","userRelationship":0,"userType":0,"userTypeCode":"JKRCL"}]},"msg":"success"}